eyantra_autoeval/__init__.py
eyantra_autoeval/console.py
eyantra_autoeval/utils/common.py
eyantra_autoeval/year/.vscode/c_cpp_properties.json
eyantra_autoeval/year/.vscode/settings.json
eyantra_autoeval/year/y2022/SD/task0/evaluator.py
eyantra_autoeval/year/y2023/AB/task0/evaluator.py
eyantra_autoeval/year/y2023/AB/task2A/evaluator.py
eyantra_autoeval/year/y2023/AB/task2B/evaluator.py
eyantra_autoeval/year/y2023/CL/task0/evaluator.py
eyantra_autoeval/year/y2023/CL/task1A/evaluator.py
eyantra_autoeval/year/y2023/CL/task1B/evaluator.py
eyantra_autoeval/year/y2023/CL/task1C/evaluator.py
eyantra_autoeval/year/y2023/CL/task2A/evaluator.py
eyantra_autoeval/year/y2023/CL/task2B/evaluator.py
eyantra_autoeval/year/y2023/HB/task0/evaluator.py
eyantra_autoeval/year/y2023/LD/task0/evaluator.py
eyantra_autoeval/year/y2024/EB/task0/evaluator.py
eyantra_autoeval/year/y2024/EB/task2A/evaluator.py
eyantra_autoeval/year/y2024/EB/task2B/evaluator.py
eyantra_autoeval/year/y2024/LB/task0/evaluator.py
eyantra_autoeval/year/y2024/LB/task1A/evaluator.py
eyantra_autoeval/year/y2024/LB/task1B/evaluator.py
eyantra_autoeval/year/y2024/LB/task1C/evaluator.py
eyantra_autoeval/year/y2024/LB/task2A/evaluator.py
eyantra_autoeval/year/y2024/LB/task2B/evaluator.py
eyantra_autoeval/year/y2024/LB/task3B/evaluator.py
eyantra_autoeval/year/y2024/ROS/task0/evaluator.py
eyantra_autoeval/year/y2024/WD/.vscode/c_cpp_properties.json
eyantra_autoeval/year/y2024/WD/.vscode/settings.json
eyantra_autoeval/year/y2024/WD/task0/.vscode/c_cpp_properties.json
eyantra_autoeval/year/y2024/WD/task0/.vscode/settings.json
eyantra_autoeval/year/y2024/WD/task0/evaluator.py
eyantra_autoeval/year/y2025/CB/task0/evaluator.py
eyantra_autoeval/year/y2025/HB/task0/evaluator.py
eyantra_autoeval/year/y2025/KB/task0/evaluator.py
eyantra_autoeval/year/y2025/KC/task0/evaluator.py
eyantra_autoeval/year/y2025/KC/task1A/evaluator.py
eyantra_autoeval/year/y2025/KC/task1B/evaluator.py
eyantra_autoeval/year/y2025/KC/task1C/evaluator.py
eyantra_autoeval-0.1.62.dist-info/METADATA
eyantra_autoeval-0.1.62.dist-info/WHEEL
eyantra_autoeval-0.1.62.dist-info/entry_points.txt
eyantra_autoeval-0.1.62.dist-info/RECORD
